[
    {
        "component_name": "Hair",
        "root_vs": "e8425f64cfb887cd",
        "draw_vb": "18d9ad82",
        "position_vb": "fd24333c",
        "blend_vb": "4b1780bb",
        "texcoord_vb": "b7b84af4",
        "ib": "16e76a8a",
        "object_indexes": [
            0
        ],
        "object_classifications": [
            "A"
        ],
        "texture_hashes": [
            [
                [
                    "Diffuse",
                    ".dds",
                    "7fcd70ea"
                ],
                [
                    "LightMap",
                    ".dds",
                    "93279a4a"
                ]
            ]
        ]
    },
    {
        "component_name": "Head",
        "root_vs": "e8425f64cfb887cd",
        "draw_vb": "87f9b9c3",
        "position_vb": "db053da4",
        "blend_vb": "53070a34",
        "texcoord_vb": "615aee40",
        "ib": "9af18b75",
        "object_indexes": [
            0,
            12810
        ],
        "object_classifications": [
            "A",
            "B"
        ],
        "texture_hashes": [
            [
                [
                    "Diffuse",
                    ".dds",
                    "945d61df"
                ]
            ],
            []
        ]
    },
    {
        "component_name": "Body",
        "root_vs": "e8425f64cfb887cd",
        "draw_vb": "79a43d63",
        "position_vb": "ca538103",
        "blend_vb": "b889667f",
        "texcoord_vb": "77a2f3bf",
        "ib": "98dbd548",
        "object_indexes": [
            0,
            44043
        ],
        "object_classifications": [
            "A",
            "B"
        ],
        "comments": [
            "Body parts A and B use the same textures except for the StockingMap that's only used on A"
        ],
        "texture_hashes": [
            [
                [
                    "Diffuse",
                    ".dds",
                    "48fca7f8"
                ],
                [
                    "LightMap",
                    ".dds",
                    "21d34147"
                ],
                [
                    "StockingMap",
                    ".dds",
                    "883e4c54"
                ]
            ],
            []
        ]
    }
]