[
    {
        "component_name": "Hair",
        "root_vs": "e8425f64cfb887cd",
        "draw_vb": "acf975aa",
        "position_vb": "b591da57",
        "blend_vb": "031da129",
        "texcoord_vb": "cc05d7f3",
        "ib": "5d61b5b0",
        "object_indexes": [
            0
        ],
        "object_classifications": [
            "A"
        ],
        "texture_hashes": [
            [
                [
                    "Diffuse",
                    ".dds",
                    "02394eab"
                ],
                [
                    "LightMap",
                    ".dds",
                    "98fd88ae"
                ],
                [
                    "ShadowRamp",
                    ".jpg",
                    "58d2635b"
                ]
            ]
        ],
        "first_vs": "442888ec07379143"
    },
    {
        "component_name": "Head",
        "root_vs": "e8425f64cfb887cd",
        "draw_vb": "cf9c7841",
        "position_vb": "8ed66c8a",
        "blend_vb": "5bfc6e67",
        "texcoord_vb": "f01e58df",
        "ib": "a547f1ac",
        "object_indexes": [
            0,
            13443
        ],
        "object_classifications": [
            "A",
            "B"
        ],
        "texture_hashes": [
            [
                [
                    "Diffuse",
                    ".dds",
                    "1e764817"
                ],
                [
                    "LightMap",
                    ".dds",
                    "bb5905b2"
                ],
                [
                    "Shadow",
                    ".dds",
                    "fd91fe9f"
                ],
                [
                    "t3",
                    ".dds",
                    "6567c9c0"
                ]
            ],
            [
                [
                    "Diffuse",
                    ".dds",
                    "fd91fe9f"
                ],
                [
                    "LightMap",
                    ".dds",
                    "bb5905b2"
                ],
                [
                    "Shadow",
                    ".dds",
                    "6567c9c0"
                ]
            ]
        ],
        "first_vs": "d45c2196dc7e6526"
    },
    {
        "component_name": "Body",
        "root_vs": "e8425f64cfb887cd",
        "draw_vb": "2c5a53ab",
        "position_vb": "9fadefcb",
        "blend_vb": "814e4894",
        "texcoord_vb": "ab30fd81",
        "ib": "be813760",
        "object_indexes": [
            0
        ],
        "object_classifications": [
            "A"
        ],
        "texture_hashes": [
            [
                [
                    "Diffuse",
                    ".dds",
                    "f256d83c"
                ],
                [
                    "LightMap",
                    ".dds",
                    "5e3149d6"
                ],
                [
                    "ShadowRamp",
                    ".jpg",
                    "078177f1"
                ]
            ]
        ],
        "first_vs": "8fdb5b35d9d54399"
    }
]